llm_templates/__init__.py
llm_templates/common.py
llm_templates/formatter.py
llm_templates/formats/__init__.py
llm_templates/formats/cohere.py
llm_templates/formats/gemma.py
llm_templates/formats/llama2.py
llm_templates/formats/llama3.py
llm_templates/formats/llama31.py
llm_templates/formats/mistral.py
llm_templates/formats/phi3.py
llm_templates/formats/zephyr.py
llm_templates-0.1.12.dist-info/LICENSE
llm_templates-0.1.12.dist-info/METADATA
llm_templates-0.1.12.dist-info/WHEEL
llm_templates-0.1.12.dist-info/top_level.txt
llm_templates-0.1.12.dist-info/RECORD
