Metadata-Version: 2.1
Name: llm-templates
Version: 0.1.12
Summary: Instruction/chat prompts creation library for text generation LLMs. It supports local and Hugging Face models.
Home-page: https://github.com/jpmanson/llm_templates
Author: Juan Pablo Manson
Author-email: jpmanson@gmail.com
Requires-Python: >=3.9
License-File: LICENSE
Requires-Dist: requests >=2.28.0
Requires-Dist: Jinja2 >=2.11.3
